edgeseraser/__init__.py
edgeseraser/disparity.py
edgeseraser/misc/__init__.py
edgeseraser/misc/backend.py
edgeseraser/misc/fast_math.py
edgeseraser/misc/matrix.py
edgeseraser/misc/typing.py
edgeseraser/noise_score.py
edgeseraser/polya.py
edgeseraser/polya_tools/__init__.py
edgeseraser/polya_tools/numba_tools.py
edgeseraser/polya_tools/statistics.py
edgeseraser/py.typed
edgeseraser-0.6.0.dist-info/WHEEL
edgeseraser-0.6.0.dist-info/METADATA
edgeseraser-0.6.0.dist-info/RECORD
