Metadata-Version: 2.1
Name: edgeseraser
Version: 0.6.0
Summary: A short description of the project
Home-page: https://devmessias.github.io/edgeseraser
License: MIT
Author: Bruno Messias
Author-email: devmessias@gmail.com
Requires-Python: >=3.7.1,<3.11
Classifier: Development Status :: 4 - Beta
Classifier: Intended Audience :: Developers
Classifier: License :: OSI Approved :: MIT License
Classifier: Operating System :: OS Independent
Classifier: Programming Language :: Python
Classifier: Programming Language :: Python :: 3
Classifier: Programming Language :: Python :: 3.10
Classifier: Programming Language :: Python :: 3.7
Classifier: Programming Language :: Python :: 3.8
Classifier: Programming Language :: Python :: 3.9
Classifier: Topic :: Software Development :: Libraries :: Python Modules
Classifier: Typing :: Typed
Requires-Dist: igraph
Requires-Dist: llvmlite (>=0.37.0)
Requires-Dist: networkx
Requires-Dist: numba
Requires-Dist: numpy
Requires-Dist: scipy
Requires-Dist: typing_extensions
Project-URL: Documentation, https://devmessias.github.io/edgeseraser
Project-URL: Repository, https://github.com/devmessias/edgeseraser
